ambars_sudoku_solver/__init__.py
ambars_sudoku_solver/helpers/__init__.py
ambars_sudoku_solver/helpers/errors.py
ambars_sudoku_solver/helpers/generate_problems.py
ambars_sudoku_solver/helpers/timer.py
ambars_sudoku_solver/helpers/types.py
ambars_sudoku_solver/settings.py
ambars_sudoku_solver/solvers/backtracking_solution.py
ambars_sudoku_solver/solvers/no_backtracking_solution.py
ambars_sudoku_solver/sudoku_cube.py
ambars_sudoku_solver-0.1.0.dist-info/LICENSE
ambars_sudoku_solver-0.1.0.dist-info/METADATA
ambars_sudoku_solver-0.1.0.dist-info/WHEEL
ambars_sudoku_solver-0.1.0.dist-info/RECORD
