Metadata-Version: 2.1
Name: ambars-sudoku-solver
Version: 0.1.0
Summary: Package for solving and creating sudoku problems
License: MIT
Author: Ambar Das
Author-email: ambardeepdas@yahoo.com
Requires-Python: >=3.11,<4.0
Classifier: License :: OSI Approved :: MIT License
Classifier: Programming Language :: Python :: 3
Classifier: Programming Language :: Python :: 3.11
